duck_math_py/__init__.py
duck_math_py/calc.py
tests/__init__.py
tests/test_calc.py
duck_math_py-0.1.0.dist-info/LICENSE
duck_math_py-0.1.0.dist-info/METADATA
duck_math_py-0.1.0.dist-info/WHEEL
duck_math_py-0.1.0.dist-info/top_level.txt
duck_math_py-0.1.0.dist-info/RECORD
